yt_stream_recorder/__init__.py
yt_stream_recorder/__main__.py
yt_stream_recorder/main.py
yt_stream_recorder/setup.py
yt_stream_recorder/icons/icon.ico
yt_stream_recorder/icons/icon.svg
yt_stream_recorder-22.2.6.dist-info/METADATA
yt_stream_recorder-22.2.6.dist-info/WHEEL
yt_stream_recorder-22.2.6.dist-info/RECORD
