Metadata-Version: 2.1
Name: yt_stream_recorder
Version: 22.2.6
Summary: tool for recording youtube streams
Project-URL: Homepage, https://github.com/gmankab/yt_stream_recorder
Project-URL: Documentation, https://github.com/gmankab/yt_stream_recorder
Project-URL: Bug Tracker, https://github.com/gmankab/yt_stream_recorder/issues
Author-email: gmanka <gmankab@gmail.com>
Classifier: License :: OSI Approved :: GNU General Public License v3 (GPLv3)
Classifier: Operating System :: OS Independent
Classifier: Programming Language :: Python :: 3
Requires-Python: >=3.10
Requires-Dist: betterdata
Requires-Dist: easyselect
Requires-Dist: gmanka-yml
Requires-Dist: rich
Requires-Dist: yt-dlp
